pubchemTools/__init__.py
pubchemTools/ghs_code.py
pubchemTools/pubchemTools.py
pubchemtools-1.26.dist-info/METADATA
pubchemtools-1.26.dist-info/WHEEL
pubchemtools-1.26.dist-info/top_level.txt
pubchemtools-1.26.dist-info/RECORD
