Metadata-Version: 2.4
Name: pubchemTools
Version: 1.26
Summary: Helper functions to retrieve and handle pubchem records
Author: Tamás Haraszti
Author-email: haraszti@dwi.rwth-aachen.de
License: CC-BY(4) (https://creativecommons.org/licenses/by/4.0/)
Requires-Dist: dictDigUtils
Requires-Dist: requests>2
